facial_recognition/__init__.py
facial_recognition/add_faces.py
facial_recognition/cli.py
facial_recognition/models_utils.py
facial_recognition/recognizer.py
facial_recognition/remove_faces.py
facial_recognition/setup_model.py
facial_recognition-0.2.0.dist-info/METADATA
facial_recognition-0.2.0.dist-info/WHEEL
facial_recognition-0.2.0.dist-info/entry_points.txt
facial_recognition-0.2.0.dist-info/licenses/LICENSE.txt
facial_recognition-0.2.0.dist-info/RECORD
