Metadata-Version: 2.4
Name: facial_recognition
Version: 0.2.0
Summary: Most effective and easiest to install python library for recognising faces in images or videos
Project-URL: Homepage, https://github.com/Rubarion/facial_recognition
Author-email: Sreehari P V <rubarion@gmail.com>
License-File: LICENSE.txt
Classifier: License :: OSI Approved :: MIT License
Classifier: Operating System :: OS Independent
Classifier: Programming Language :: Python :: 3
Requires-Python: >=3
